fabricatio_anki-0.2.12.data/scripts/apc
fabricatio_anki-0.2.12.dist-info/METADATA
fabricatio_anki-0.2.12.dist-info/WHEEL
fabricatio_anki-0.2.12.dist-info/licenses/LICENSE
fabricatio_anki/__init__.py
fabricatio_anki/actions/__init__.py
fabricatio_anki/actions/topic_analysis.py
fabricatio_anki/capabilities/__init__.py
fabricatio_anki/capabilities/generate_analysis.py
fabricatio_anki/capabilities/generate_deck.py
fabricatio_anki/config.py
fabricatio_anki/models/__init__.py
fabricatio_anki/models/deck.py
fabricatio_anki/models/template.py
fabricatio_anki/models/topic_analysis.py
fabricatio_anki/py.typed
fabricatio_anki/rust.cpython-312-aarch64-linux-gnu.so
fabricatio_anki/rust.pyi
fabricatio_anki/workflows/__init__.py
fabricatio_anki-0.2.12.dist-info/RECORD
