Metadata-Version: 2.4
Name: fabricatio-anki
Version: 0.2.12
Requires-Dist: fabricatio-core
Requires-Dist: fabricatio-capabilities
License-File: LICENSE
Summary: An extension of fabricatio, which brings up the capability of creating fully explainned anki deck package
Author-email: Whth <zettainspector@foxmail.com>
Requires-Python: >=3.12, <3.15
Project-URL: Homepage, https://github.com/Whth/fabricatio
Project-URL: Repository, https://github.com/Whth/fabricatio
Project-URL: Issues, https://github.com/Whth/fabricatio/issues
